pyrevm_contract/__init__.py
pyrevm_contract/abi.py
pyrevm_contract/contract.py
pyrevm_contract/revm.py
pyrevm_contract-0.3.1.dist-info/LICENSE
pyrevm_contract-0.3.1.dist-info/METADATA
pyrevm_contract-0.3.1.dist-info/WHEEL
pyrevm_contract-0.3.1.dist-info/top_level.txt
pyrevm_contract-0.3.1.dist-info/RECORD
