Metadata-Version: 2.1
Name: pyrevm-contract
Version: 0.3.1
Summary: Contract wrapper for pyrevm
Home-page: https://github.com/jalbrekt85/pyrevm-contract
Author: jalbrekt85
Author-email: jcalbrecht85@gmail.com
Classifier: Programming Language :: Python :: 3
Classifier: License :: OSI Approved :: MIT License
Classifier: Operating System :: OS Independent
Requires-Python: >=3.9
License-File: LICENSE
Requires-Dist: pyrevm ==0.3.0
Requires-Dist: eth-abi
Requires-Dist: eth-utils
Requires-Dist: eth-hash[pycryptodome]
